cnn_panagiota/__init__.py
cnn_panagiota/final_cnn.py
cnn_panagiota-0.0.2.dist-info/METADATA
cnn_panagiota-0.0.2.dist-info/WHEEL
cnn_panagiota-0.0.2.dist-info/top_level.txt
cnn_panagiota-0.0.2.dist-info/RECORD
