Metadata-Version: 2.1
Name: cnn-panagiota
Version: 0.0.2
Summary: CNN for Kannada MNIST - Pytorch
Home-page: https://github.com/PanayiotaK/Kannada-CNN
Author: Panagiota Konstantinou
Author-email: constantinoupana@gmail.com
License: UNKNOWN
Keywords: artificial intelligence,deep learning,CNN,Kannada
Platform: UNKNOWN
Classifier: Development Status :: 1 - Planning
Classifier: Intended Audience :: Developers
Classifier: Topic :: Scientific/Engineering :: Artificial Intelligence
Classifier: Operating System :: Unix
Classifier: Operating System :: MacOS :: MacOS X
Classifier: Operating System :: Microsoft :: Windows
Classifier: Programming Language :: Python :: 3.10
Requires-Dist: matplotlib
Requires-Dist: numpy
Requires-Dist: pandas
Requires-Dist: torch (>=1.10)
Requires-Dist: torchvision
Requires-Dist: scikit-learn
